pitch_dark/404.html
pitch_dark/__init__.py
pitch_dark/base.html
pitch_dark/footer.html
pitch_dark/head.html
pitch_dark/main.html
pitch_dark/mkdocs_theme.yml
pitch_dark/nav.html
pitch_dark/page.html
pitch_dark/scripts.html
pitch_dark/css/style.css
pitch_dark/js/script.js
pitch_dark/vendor/bootstrap/js/bootstrap.min.js
pitch_dark/vendor/bootswatch/css/bootstrap.min.css
pitch_dark/vendor/codrops/js/cbpAnimatedHeader.js
pitch_dark/vendor/codrops/js/classie.js
pitch_dark/vendor/jasny-bootstrap/css/jasny-bootstrap.min.css
pitch_dark/vendor/jasny-bootstrap/js/jasny-bootstrap.min.js
pitch_dark/vendor/jquery/js/jquery.min.js
pitch_dark/vendor/jquery-tagcanvas/js/jquery.tagcanvas.min.js
pitch_dark/vendor/reactiveraven/js/jqBootstrapValidation.js
pitch_dark/vendor/typed.js/js/typed.min.js
mkdocs_pitch_dark-0.0.3.dist-info/COPYING
mkdocs_pitch_dark-0.0.3.dist-info/METADATA
mkdocs_pitch_dark-0.0.3.dist-info/WHEEL
mkdocs_pitch_dark-0.0.3.dist-info/entry_points.txt
mkdocs_pitch_dark-0.0.3.dist-info/top_level.txt
mkdocs_pitch_dark-0.0.3.dist-info/RECORD
