Metadata-Version: 2.1
Name: mkdocs-pitch-dark
Version: 0.0.3
Summary: Dark Minimal Theme for MkDocs
Home-page: https://gitlab.com/lramage/pitch-dark
Author: Lucas Ramage
Author-email: ramage.lucas@protonmail.com
License: GPL-3.0
Platform: UNKNOWN
